odoo/addons/ssi_l10n_id_partner_identification_kependudukan/README.rst
odoo/addons/ssi_l10n_id_partner_identification_kependudukan/__init__.py
odoo/addons/ssi_l10n_id_partner_identification_kependudukan/__manifest__.py
odoo/addons/ssi_l10n_id_partner_identification_kependudukan/data/res_partner_id_category_data.xml
odoo/addons/ssi_l10n_id_partner_identification_kependudukan/models/__init__.py
odoo/addons/ssi_l10n_id_partner_identification_kependudukan/models/res_partner.py
odoo/addons/ssi_l10n_id_partner_identification_kependudukan/static/description/icon.png
odoo14_addon_ssi_l10n_id_partner_identification_kependudukan-14.0.1.0.2.dev1.dist-info/METADATA
odoo14_addon_ssi_l10n_id_partner_identification_kependudukan-14.0.1.0.2.dev1.dist-info/WHEEL
odoo14_addon_ssi_l10n_id_partner_identification_kependudukan-14.0.1.0.2.dev1.dist-info/top_level.txt
odoo14_addon_ssi_l10n_id_partner_identification_kependudukan-14.0.1.0.2.dev1.dist-info/RECORD
